narkdown/__init__.py
narkdown/__main__.py
narkdown/cli.py
narkdown/constants.py
narkdown/exporter.py
narkdown/utils.py
narkdown/notion/__init__.py
narkdown/notion/block.py
narkdown/notion/client.py
narkdown/notion/collection.py
narkdown/notion/logger.py
narkdown/notion/maps.py
narkdown/notion/markdown.py
narkdown/notion/monitor.py
narkdown/notion/operations.py
narkdown/notion/records.py
narkdown/notion/settings.py
narkdown/notion/smoke_test.py
narkdown/notion/space.py
narkdown/notion/store.py
narkdown/notion/user.py
narkdown/notion/utils.py
narkdown-1.3.5.dist-info/LICENSE
narkdown-1.3.5.dist-info/METADATA
narkdown-1.3.5.dist-info/WHEEL
narkdown-1.3.5.dist-info/top_level.txt
narkdown-1.3.5.dist-info/RECORD
