Metadata-Version: 2.1
Name: narkdown
Version: 1.3.5
Summary: A tool to use Notion as a Markdown editor.
Home-page: https://github.com/younho9/narkdown
Author: younho9
Author-email: younho9.choo@gmail.com
License: UNKNOWN
Keywords: notion,github,markdown
Platform: UNKNOWN
Classifier: Programming Language :: Python :: 3.5
Classifier: Programming Language :: Python :: 3.6
Classifier: Programming Language :: Python :: 3.7
Classifier: Programming Language :: Python :: 3.8
Classifier: Programming Language :: Python :: 3.9
Classifier: License :: OSI Approved :: MIT License
Classifier: Operating System :: OS Independent
Requires-Python: >=3.5
Requires-Dist: beautifulsoup4 (==4.9.3)
Requires-Dist: bs4 (==0.0.1)
Requires-Dist: cached-property (==1.5.2)
Requires-Dist: certifi (==2020.12.5)
Requires-Dist: chardet (==4.0.0)
Requires-Dist: commonmark (==0.9.1)
Requires-Dist: dictdiffer (==0.8.1)
Requires-Dist: idna (==2.10)
Requires-Dist: python-slugify (==4.0.1)
Requires-Dist: pytz (==2021.1)
Requires-Dist: requests (==2.25.1)
Requires-Dist: soupsieve (==2.2.1)
Requires-Dist: text-unidecode (==1.3)
Requires-Dist: tzlocal (==2.1)
Requires-Dist: urllib3 (==1.26.4)
